TracShortcutIconPlugin-0.3.dist-info/METADATA
TracShortcutIconPlugin-0.3.dist-info/RECORD
TracShortcutIconPlugin-0.3.dist-info/WHEEL
TracShortcutIconPlugin-0.3.dist-info/entry_points.txt
TracShortcutIconPlugin-0.3.dist-info/top_level.txt
tracshortcuticon/__init__.py
tracshortcuticon/plugin.py
